reqio/__init__.py
reqio/ready_request.py
reqio/pools/__init__.py
reqio/pools/core_pool.py
reqio/pools/default_pool.py
reqio/pools/html_pool.py
reqio/pools/png_pool.py
reqio/pools/svg_pool.py
reqio/toolkit/__init__.py
reqio/toolkit/name.py
reqio-300.0.0.dist-info/LICENSE
reqio-300.0.0.dist-info/METADATA
reqio-300.0.0.dist-info/WHEEL
reqio-300.0.0.dist-info/top_level.txt
reqio-300.0.0.dist-info/RECORD
