Metadata-Version: 2.1
Name: reqio
Version: 300.0.0
Summary: reqio Library
Author: Duckling Dean
Author-email: duckling.dean@proton.me
Project-URL: Source, https://github.com/DucklingDean/reqio
License-File: LICENSE
Requires-Dist: requests <3.0.0,>=2.32.2
Requires-Dist: fake-useragent ==1.5.1
